{"status": "done", "progress": 40, "message": "Computing model summaries", "modules": ["phonetic_normalization", "language_aware_normalization", "balanced_tokenization", "switch_point_encoding"], "models": ["nllb"], "dataset_name": "upload_98341ce937cf48beb8acdee62059181c", "uploaded_filename": "upload_98341ce937cf48beb8acdee62059181c.csv", "batch_size": 32, "results": {"job_id": "98341ce937cf48beb8acdee62059181c", "dataset_name": "upload_98341ce937cf48beb8acdee62059181c", "preprocessing": {"requested_modules": ["phonetic_normalization", "language_aware_normalization", "balanced_tokenization", "switch_point_encoding"], "active_modules": ["phonetic_normalization", "language_aware_normalization", "balanced_tokenization", "switch_point_encoding"], "pipeline_config": {"enabled": {"balanced_tokenization": true, "language_identification_tagging": false, "language_aware_normalization": true, "transliteration": false, "switch_point_encoding": true, "code_switch_augmentation": false, "context_aware_subword_sampling": false, "phonetic_normalization": true, "script_unification": false}, "pipeline_order": ["phonetic_normalization", "language_aware_normalization", "script_unification", "transliteration", "balanced_tokenization", "language_identification_tagging", "switch_point_encoding", "context_aware_subword_sampling"], "module_configs": {}, "random_seed": 42}}, "processed_rows": 2766, "labelled_rows": 2766, "models": {"nllb": {"model_label": "NLLB", "model_name": "facebook/nllb-200-distilled-600M", "evaluated_rows": 2766, "sampled_rows": 2766, "avg_token_count": 88.823571945047, "avg_switch_token_count": 0.0, "avg_embedding_norm": 7.6189238485528, "avg_attention_to_switch_tokens": null, "avg_attention_from_switch_tokens": null, "accuracy": 0.5213304410701374, "macro_f1": 0.45645913954462664, "per_class": {"negative": {"precision": 0.25121951219512195, "recall": 0.1889908256880734, "f1": 0.2157068062827225, "support": 545}, "neutral": {"precision": 0.5934379457917262, "recall": 0.6742301458670988, "f1": 0.6312594840667678, "support": 1234}, "positive": {"precision": 0.5314465408805031, "recall": 0.513677811550152, "f1": 0.5224111282843895, "support": 987}}, "confusion_matrix": [[103, 230, 212], [167, 832, 235], [140, 340, 507]], "samples": [{"text": "module, ek program hoti [SWITCH_EN_HI] \u0939\u0948, jismen [SWITCH_HI_EN] ya to source code ya machine language [SWITCH_EN_HI] \u0915\u0947 [SWITCH_HI_EN] form men instructions nihit [SWITCH_EN_HI] \u0939\u094b \u0924\u0947 [SWITCH_HI_EN] hain.", "actual_class": 1, "actual_label": "neutral", "predicted_class": 0, "predicted_label": "negative", "confidence": null, "token_count": 83, "switch_token_count": 0, "attention_to_switch_tokens": null, "attention_from_switch_tokens": null, "token_texts": ["eng_Latn", "\u2581module", ",", "\u2581ek", "\u2581program", "\u2581ho", "ti", "\u2581[", "SW", "IT", "CH", "_", "EN", "_", "HI", "]", "\u2581\u0939\u0948", ",", "\u2581jis", "men", "\u2581[", "SW", "IT", "CH", "_", "HI", "_", "EN", "]", "\u2581ya", "\u2581to", "\u2581source", "\u2581code", "\u2581ya", "\u2581machine", "\u2581language", "\u2581[", "SW", "IT", "CH", "_", "EN", "_", "HI", "]", "\u2581\u0915\u0947", "\u2581[", "SW", "IT", "CH", "_", "HI", "_", "EN", "]", "\u2581form", "\u2581men", "\u2581instructions", "\u2581nih", "it", "\u2581[", "SW", "IT", "CH", "_", "EN", "_", "HI", "]", "\u2581\u0939\u094b", "\u2581\u0924\u0947", "\u2581[", "SW", "IT", "CH", "_", "HI", "_", "EN", "]", "\u2581hain", ".", "</s>"]}, {"text": "\u0914\u0930 \u0939\u092e\u0928\u0947 \u0914\u092e\u0947 samood \u0915\u0947 pas \u0909\u0928\u0915\u0947 \u092d\u093e \u0908 saleh [SWITCH_HI_EN] ko [SWITCH_EN_HI] \u092a\u0948 \u092e\u094d \u092c\u0930\u094d banakar \u092d\u0947 \u091c [SWITCH_HI_EN] to [SWITCH_EN_HI] \u0909\u0928\u094d \u0939\u094b\u0902 \u0928\u0947 apni [SWITCH_HI_EN] aum se kaha ae [SWITCH_EN_HI] \u092e\u0947 \u0930\u0940 [SWITCH_HI_EN] aum uda hi [SWITCH_EN_HI] \u0915\u0940 \u092a\u0930\u0938\u094d \u0924\u093f \u0936\u094d [SWITCH_HI_EN] karo uske siva koee tumhara mabood [SWITCH_EN_HI] \u0928\u0939\u0940\u0902 usi [SWITCH_HI_EN] ne tumko zamin [SWITCH_EN_HI] \u0915\u0940 mitti [SWITCH_HI_EN] se [SWITCH_EN_HI] \u092a\u0948 \u0926 \u0915\u093f \u092f\u093e \u0914\u0930 tumko usmen \u092c\u0938\u092f [SWITCH_HI_EN] to usse [SWITCH_EN_HI] \u092e\u092b\u093f \u0930\u0924\u094d \u0915\u0940 dua mgon \u092b\u093f \u0930 uski bargah [SWITCH_HI_EN] men [SWITCH_EN_HI] \u0924\u094c \u092c [SWITCH_HI_EN] karo [SWITCH_EN_HI] \u092c\u0947 \u0936\u0915\u094d \u092e\u0947 \u0930\u093e paravardigar har \u0936\u0936\u094d \u0915\u0947 [SWITCH_HI_EN] rib [SWITCH_EN_HI] \u0914\u0930 sabki sunta \u0914\u0930 dua ubool \u0915\u0930\u0924\u093e \u0939\u0948", "actual_class": 2, "actual_label": "positive", "predicted_class": 2, "predicted_label": "positive", "confidence": null, "token_count": 321, "switch_token_count": 0, "attention_to_switch_tokens": null, "attention_from_switch_tokens": null, "token_texts": ["eng_Latn", "\u2581\u0914\u0930", "\u2581\u0939\u092e\u0928\u0947", "\u2581\u0914", "\u092e\u0947", "\u2581samo", "od", "\u2581\u0915\u0947", "\u2581pas", "\u2581\u0909\u0928\u0915\u0947", "\u2581\u092d\u093e", "\u2581\u0908", "\u2581sa", "leh", "\u2581[", "SW", "IT", "CH", "_", "HI", "_", "EN", "]", "\u2581ko", "\u2581[", "SW", "IT", "CH", "_", "EN", "_", "HI", "]", "\u2581\u092a\u0948", "\u2581\u092e\u094d", "\u2581\u092c\u0930\u094d", "\u2581ban", "akar", "\u2581\u092d\u0947", "\u2581\u091c", "\u2581[", "SW", "IT", "CH", "_", "HI", "_", "EN", "]", "\u2581to", "\u2581[", "SW", "IT", "CH", "_", "EN", "_", "HI", "]", "\u2581\u0909\u0928\u094d", "\u2581\u0939\u094b\u0902", "\u2581\u0928\u0947", "\u2581ap", "ni", "\u2581[", "SW", "IT", "CH", "_", "HI", "_", "EN", "]", "\u2581aum", "\u2581se", "\u2581kaha", "\u2581ae", "\u2581[", "SW", "IT", "CH", "_", "EN", "_", "HI", "]", "\u2581\u092e\u0947", "\u2581\u0930\u0940", "\u2581[", "SW", "IT", "CH", "_", "HI", "_", "EN", "]", "\u2581aum", "\u2581uda", "\u2581hi", "\u2581[", "SW", "IT", "CH", "_", "EN", "_", "HI", "]", "\u2581\u0915\u0940", "\u2581\u092a\u0930", "\u0938\u094d", "\u2581\u0924\u093f", "\u2581\u0936", "\u094d", "\u2581[", "SW", "IT", "CH", "_", "HI", "_", "EN", "]", "\u2581karo", "\u2581us", "ke", "\u2581si", "va", "\u2581ko", "ee", "\u2581tum", "hara", "\u2581ma", "bo", "od", "\u2581[", "SW", "IT", "CH", "_", "EN", "_", "HI", "]", "\u2581\u0928\u0939\u0940\u0902", "\u2581usi", "\u2581[", "SW", "IT", "CH", "_", "HI", "_", "EN", "]", "\u2581ne", "\u2581tum", "ko", "\u2581z", "amin", "\u2581[", "SW", "IT", "CH", "_", "EN", "_", "HI", "]", "\u2581\u0915\u0940", "\u2581mit", "ti", "\u2581[", "SW", "IT", "CH", "_", "HI", "_", "EN", "]", "\u2581se", "\u2581[", "SW", "IT", "CH", "_", "EN", "_", "HI", "]", "\u2581\u092a\u0948", "\u2581\u0926", "\u2581\u0915\u093f", "\u2581\u092f\u093e", "\u2581\u0914\u0930", "\u2581tum", "ko", "\u2581us", "men", "\u2581\u092c\u0938", "\u092f", "\u2581[", "SW", "IT", "CH", "_", "HI", "_", "EN", "]", "\u2581to", "\u2581us", "se", "\u2581[", "SW", "IT", "CH", "_", "EN", "_", "HI", "]", "\u2581\u092e", "\u092b\u093f", "\u2581\u0930", "\u0924\u094d", "\u2581\u0915\u0940", "\u2581dua", "\u2581mg", "on", "\u2581\u092b\u093f", "\u2581\u0930", "\u2581us", "ki", "\u2581bar", "gah", "\u2581[", "SW", "IT", "CH", "_", "HI", "_", "EN", "]", "\u2581men", "\u2581[", "SW", "IT", "CH", "_", "EN", "_", "HI", "]", "\u2581\u0924\u094c", "\u2581\u092c", "\u2581[", "SW", "IT", "CH", "_", "HI", "_", "EN", "]", "\u2581karo", "\u2581[", "SW", "IT", "CH", "_", "EN", "_", "HI", "]", "\u2581\u092c\u0947", "\u2581\u0936\u0915\u094d", "\u2581\u092e\u0947", "\u2581\u0930\u093e", "\u2581para", "var", "dig", "ar", "\u2581har", "\u2581\u0936", "\u0936\u094d", "\u2581\u0915\u0947", "\u2581[", "SW", "IT", "CH", "_", "HI", "_", "EN", "]", "\u2581rib", "\u2581[", "SW", "IT", "CH", "_", "EN", "_", "HI", "]", "\u2581\u0914\u0930", "\u2581sab", "ki", "\u2581sun", "ta", "\u2581\u0914\u0930", "\u2581dua", "\u2581ubo", "ol", "\u2581\u0915\u0930\u0924\u093e", "\u2581\u0939\u0948", "</s>"]}, {"text": "\u0914\u0930 [SWITCH_HI_EN] jab unhen yad [SWITCH_EN_HI] \u0926\u093f \u0932\u092f jata \u0939\u0948, [SWITCH_HI_EN] to ve yad [SWITCH_EN_HI] \u0928\u0939\u0940\u0902 \u0915\u0930\u0924\u0947,", "actual_class": 1, "actual_label": "neutral", "predicted_class": 1, "predicted_label": "neutral", "confidence": null, "token_count": 56, "switch_token_count": 0, "attention_to_switch_tokens": null, "attention_from_switch_tokens": null, "token_texts": ["eng_Latn", "\u2581\u0914\u0930", "\u2581[", "SW", "IT", "CH", "_", "HI", "_", "EN", "]", "\u2581jab", "\u2581un", "hen", "\u2581yad", "\u2581[", "SW", "IT", "CH", "_", "EN", "_", "HI", "]", "\u2581\u0926\u093f", "\u2581\u0932", "\u092f", "\u2581j", "ata", "\u2581\u0939\u0948", ",", "\u2581[", "SW", "IT", "CH", "_", "HI", "_", "EN", "]", "\u2581to", "\u2581ve", "\u2581yad", "\u2581[", "SW", "IT", "CH", "_", "EN", "_", "HI", "]", "\u2581\u0928\u0939\u0940\u0902", "\u2581\u0915\u0930\u0924\u0947", ",", "</s>"]}, {"text": "tumhen \u0968\u0966\u0967\u0967 ka ted prize mil [SWITCH_EN_HI] \u0917\u092f\u093e \u0939\u0948", "actual_class": 2, "actual_label": "positive", "predicted_class": 1, "predicted_label": "neutral", "confidence": null, "token_count": 22, "switch_token_count": 0, "attention_to_switch_tokens": null, "attention_from_switch_tokens": null, "token_texts": ["eng_Latn", "\u2581tum", "hen", "\u2581\u0968\u0966\u0967", "\u0967", "\u2581ka", "\u2581ted", "\u2581pri", "ze", "\u2581mil", "\u2581[", "SW", "IT", "CH", "_", "EN", "_", "HI", "]", "\u2581\u0917\u092f\u093e", "\u2581\u0939\u0948", "</s>"]}, {"text": "\u0909\u0928\u094d \u0939\u094b\u0902 \u0928\u0947 [SWITCH_HI_EN] bad science karne [SWITCH_EN_HI] \u0915\u0947 [SWITCH_HI_EN] lie ye delhi university [SWITCH_EN_HI] \u0915\u0947 \u0915\u093f \u0930\u094b \u0930\u093f \u092e\u0932\u094d [SWITCH_HI_EN] college [SWITCH_EN_HI] \u091a\u0932\u0947 [SWITCH_HI_EN] ge jahan [SWITCH_EN_HI] \u0907\u0928\u094d \u0939\u094b\u0902 \u0928\u0947 vijnjan [SWITCH_HI_EN] graduate [SWITCH_EN_HI] \u0915\u0940 [SWITCH_HI_EN] degree prapt [SWITCH_EN_HI] \u0915\u0940.", "actual_class": 1, "actual_label": "neutral", "predicted_class": 2, "predicted_label": "positive", "confidence": null, "token_count": 146, "switch_token_count": 0, "attention_to_switch_tokens": null, "attention_from_switch_tokens": null, "token_texts": ["eng_Latn", "\u2581\u0909\u0928\u094d", "\u2581\u0939\u094b\u0902", "\u2581\u0928\u0947", "\u2581[", "SW", "IT", "CH", "_", "HI", "_", "EN", "]", "\u2581bad", "\u2581science", "\u2581karne", "\u2581[", "SW", "IT", "CH", "_", "EN", "_", "HI", "]", "\u2581\u0915\u0947", "\u2581[", "SW", "IT", "CH", "_", "HI", "_", "EN", "]", "\u2581lie", "\u2581ye", "\u2581del", "hi", "\u2581university", "\u2581[", "SW", "IT", "CH", "_", "EN", "_", "HI", "]", "\u2581\u0915\u0947", "\u2581\u0915\u093f", "\u2581\u0930\u094b", "\u2581\u0930\u093f", "\u2581\u092e", "\u0932\u094d", "\u2581[", "SW", "IT", "CH", "_", "HI", "_", "EN", "]", "\u2581college", "\u2581[", "SW", "IT", "CH", "_", "EN", "_", "HI", "]", "\u2581\u091a\u0932\u0947", "\u2581[", "SW", "IT", "CH", "_", "HI", "_", "EN", "]", "\u2581ge", "\u2581jahan", "\u2581[", "SW", "IT", "CH", "_", "EN", "_", "HI", "]", "\u2581\u0907\u0928\u094d", "\u2581\u0939\u094b\u0902", "\u2581\u0928\u0947", "\u2581vi", "jn", "jan", "\u2581[", "SW", "IT", "CH", "_", "HI", "_", "EN", "]", "\u2581gradu", "ate", "\u2581[", "SW", "IT", "CH", "_", "EN", "_", "HI", "]", "\u2581\u0915\u0940", "\u2581[", "SW", "IT", "CH", "_", "HI", "_", "EN", "]", "\u2581degree", "\u2581pra", "pt", "\u2581[", "SW", "IT", "CH", "_", "EN", "_", "HI", "]", "\u2581\u0915\u0940", ".", "</s>"]}, {"text": "\u092b\u093f \u0930 \u0939\u092e\u0928\u0947 unhen \u092d\u0947 \u091c, taki maloom [SWITCH_HI_EN] karen [SWITCH_EN_HI] \u0915\u0940 [SWITCH_HI_EN] calculate the length se kisne yad [SWITCH_EN_HI] \u0930\u0916\u093e \u0939\u0948 \u0915\u0940 kitni \u0905\u0935\u094d \u0927\u093f tak ve \u0930\u0939\u0947", "actual_class": 2, "actual_label": "positive", "predicted_class": 0, "predicted_label": "negative", "confidence": null, "token_count": 71, "switch_token_count": 0, "attention_to_switch_tokens": null, "attention_from_switch_tokens": null, "token_texts": ["eng_Latn", "\u2581\u092b\u093f", "\u2581\u0930", "\u2581\u0939\u092e\u0928\u0947", "\u2581un", "hen", "\u2581\u092d\u0947", "\u2581\u091c", ",", "\u2581taki", "\u2581malo", "om", "\u2581[", "SW", "IT", "CH", "_", "HI", "_", "EN", "]", "\u2581karen", "\u2581[", "SW", "IT", "CH", "_", "EN", "_", "HI", "]", "\u2581\u0915\u0940", "\u2581[", "SW", "IT", "CH", "_", "HI", "_", "EN", "]", "\u2581calcula", "te", "\u2581the", "\u2581length", "\u2581se", "\u2581kis", "ne", "\u2581yad", "\u2581[", "SW", "IT", "CH", "_", "EN", "_", "HI", "]", "\u2581\u0930\u0916\u093e", "\u2581\u0939\u0948", "\u2581\u0915\u0940", "\u2581kit", "ni", "\u2581\u0905\u0935", "\u094d", "\u2581\u0927", "\u093f", "\u2581tak", "\u2581ve", "\u2581\u0930\u0939\u0947", "</s>"]}, {"text": "\u0915\u094d \u092f\u093e ap vakee raddi [SWITCH_HI_EN] men sare [SWITCH_EN_HI] \u092b\u094b \u0924\u094b \u0938\u094d [SWITCH_HI_EN] and videos [SWITCH_EN_HI] \u0916\u093f \u0938\u094d \u0915\u0928 \u091a\u0939\u094d \u0924\u0947 [SWITCH_HI_EN] hain", "actual_class": 1, "actual_label": "neutral", "predicted_class": 0, "predicted_label": "negative", "confidence": null, "token_count": 69, "switch_token_count": 0, "attention_to_switch_tokens": null, "attention_from_switch_tokens": null, "token_texts": ["eng_Latn", "\u2581\u0915\u094d", "\u2581\u092f\u093e", "\u2581ap", "\u2581vake", "e", "\u2581rad", "di", "\u2581[", "SW", "IT", "CH", "_", "HI", "_", "EN", "]", "\u2581men", "\u2581sare", "\u2581[", "SW", "IT", "CH", "_", "EN", "_", "HI", "]", "\u2581\u092b\u094b", "\u2581\u0924\u094b", "\u2581\u0938\u094d", "\u2581[", "SW", "IT", "CH", "_", "HI", "_", "EN", "]", "\u2581and", "\u2581videos", "\u2581[", "SW", "IT", "CH", "_", "EN", "_", "HI", "]", "\u2581\u0916\u093f", "\u2581\u0938\u094d", "\u2581\u0915\u0928", "\u2581\u091a", "\u0939", "\u094d", "\u2581\u0924\u0947", "\u2581[", "SW", "IT", "CH", "_", "HI", "_", "EN", "]", "\u2581hain", "</s>"]}, {"text": "malabar men [SWITCH_EN_HI] \u0916\u0941 \u0926\u0948 \u0915\u0947 kamron [SWITCH_HI_EN] men [SWITCH_EN_HI] \u0930\u0916\u0947 [SWITCH_HI_EN] hue bare- bare bartan mile hain jinme [SWITCH_EN_HI] \u0936\u0935\u094d \u0930\u0916\u0947 jate [SWITCH_HI_EN] the.", "actual_class": 1, "actual_label": "neutral", "predicted_class": 0, "predicted_label": "negative", "confidence": null, "token_count": 82, "switch_token_count": 0, "attention_to_switch_tokens": null, "attention_from_switch_tokens": null, "token_texts": ["eng_Latn", "\u2581mala", "bar", "\u2581men", "\u2581[", "SW", "IT", "CH", "_", "EN", "_", "HI", "]", "\u2581\u0916\u0941", "\u2581\u0926\u0948", "\u2581\u0915\u0947", "\u2581kam", "ron", "\u2581[", "SW", "IT", "CH", "_", "HI", "_", "EN", "]", "\u2581men", "\u2581[", "SW", "IT", "CH", "_", "EN", "_", "HI", "]", "\u2581\u0930\u0916\u0947", "\u2581[", "SW", "IT", "CH", "_", "HI", "_", "EN", "]", "\u2581hue", "\u2581bare", "-", "\u2581bare", "\u2581b", "artan", "\u2581mile", "\u2581hain", "\u2581jin", "me", "\u2581[", "SW", "IT", "CH", "_", "EN", "_", "HI", "]", "\u2581\u0936", "\u0935\u094d", "\u2581\u0930\u0916\u0947", "\u2581jate", "\u2581[", "SW", "IT", "CH", "_", "HI", "_", "EN", "]", "\u2581the", ".", "</s>"]}, {"text": "\u0914\u0930 \u0927\u0930\u094d \u0924\u093f [SWITCH_HI_EN] ko ek samatal desolate maidan banakar [SWITCH_EN_HI] \u091b\u094b \u0930\u0947 \u0917", "actual_class": 0, "actual_label": "negative", "predicted_class": 1, "predicted_label": "neutral", "confidence": null, "token_count": 37, "switch_token_count": 0, "attention_to_switch_tokens": null, "attention_from_switch_tokens": null, "token_texts": ["eng_Latn", "\u2581\u0914\u0930", "\u2581\u0927\u0930\u094d", "\u2581\u0924\u093f", "\u2581[", "SW", "IT", "CH", "_", "HI", "_", "EN", "]", "\u2581ko", "\u2581ek", "\u2581sam", "atal", "\u2581des", "ola", "te", "\u2581ma", "idan", "\u2581ban", "akar", "\u2581[", "SW", "IT", "CH", "_", "EN", "_", "HI", "]", "\u2581\u091b\u094b", "\u2581\u0930\u0947", "\u2581\u0917", "</s>"]}, {"text": "\u092e\u0941 \u091d\u0947 \u0926\u0947 \u0916\u094d \u0928\u0947 \u0915\u0947 [SWITCH_HI_EN] lie jab ap [SWITCH_EN_HI] \u0911\u0928\u094d \u0932\u0948 \u0928\u094d [SWITCH_HI_EN] ho [SWITCH_EN_HI] \u0927\u0928\u094d \u092f\u094d \u0935\u0926\u094d!", "actual_class": 2, "actual_label": "positive", "predicted_class": 0, "predicted_label": "negative", "confidence": null, "token_count": 61, "switch_token_count": 0, "attention_to_switch_tokens": null, "attention_from_switch_tokens": null, "token_texts": ["eng_Latn", "\u2581\u092e\u0941", "\u2581\u091d", "\u0947", "\u2581\u0926\u0947", "\u2581\u0916", "\u094d", "\u2581\u0928\u0947", "\u2581\u0915\u0947", "\u2581[", "SW", "IT", "CH", "_", "HI", "_", "EN", "]", "\u2581lie", "\u2581jab", "\u2581ap", "\u2581[", "SW", "IT", "CH", "_", "EN", "_", "HI", "]", "\u2581\u0911", "\u0928\u094d", "\u2581\u0932\u0948", "\u2581\u0928\u094d", "\u2581[", "SW", "IT", "CH", "_", "HI", "_", "EN", "]", "\u2581ho", "\u2581[", "SW", "IT", "CH", "_", "EN", "_", "HI", "]", "\u2581\u0927", "\u0928\u094d", "\u2581\u092f", "\u094d", "\u2581\u0935", "\u0926\u094d", "!", "</s>"]}, {"text": "jo azasartapa un logon [SWITCH_EN_HI] \u0915\u0947 [SWITCH_HI_EN] lie guidance v mercy [SWITCH_EN_HI] \u0939\u0948", "actual_class": 2, "actual_label": "positive", "predicted_class": 1, "predicted_label": "neutral", "confidence": null, "token_count": 43, "switch_token_count": 0, "attention_to_switch_tokens": null, "attention_from_switch_tokens": null, "token_texts": ["eng_Latn", "\u2581jo", "\u2581az", "as", "arta", "pa", "\u2581un", "\u2581log", "on", "\u2581[", "SW", "IT", "CH", "_", "EN", "_", "HI", "]", "\u2581\u0915\u0947", "\u2581[", "SW", "IT", "CH", "_", "HI", "_", "EN", "]", "\u2581lie", "\u2581guidance", "\u2581v", "\u2581mercy", "\u2581[", "SW", "IT", "CH", "_", "EN", "_", "HI", "]", "\u2581\u0939\u0948", "</s>"]}, {"text": "france men is ek deed [SWITCH_EN_HI] \u0915\u0940 [SWITCH_HI_EN] news bijli [SWITCH_EN_HI] \u0915\u0940 tarah \u092b\u0948 \u0932\u094d [SWITCH_HI_EN] jati [SWITCH_EN_HI] \u0939\u0948 \u0914\u0930 [SWITCH_HI_EN] people [SWITCH_EN_HI] \u092d\u094d \u0930\u092e\u094d [SWITCH_HI_EN] se mut hokar pride mahsoos [SWITCH_EN_HI] \u0915\u0930\u0924\u0947 [SWITCH_HI_EN] hain", "actual_class": 2, "actual_label": "positive", "predicted_class": 2, "predicted_label": "positive", "confidence": null, "token_count": 125, "switch_token_count": 0, "attention_to_switch_tokens": null, "attention_from_switch_tokens": null, "token_texts": ["eng_Latn", "\u2581france", "\u2581men", "\u2581is", "\u2581ek", "\u2581deed", "\u2581[", "SW", "IT", "CH", "_", "EN", "_", "HI", "]", "\u2581\u0915\u0940", "\u2581[", "SW", "IT", "CH", "_", "HI", "_", "EN", "]", "\u2581news", "\u2581bij", "li", "\u2581[", "SW", "IT", "CH", "_", "EN", "_", "HI", "]", "\u2581\u0915\u0940", "\u2581tara", "h", "\u2581\u092b\u0948", "\u2581\u0932", "\u094d", "\u2581[", "SW", "IT", "CH", "_", "HI", "_", "EN", "]", "\u2581jati", "\u2581[", "SW", "IT", "CH", "_", "EN", "_", "HI", "]", "\u2581\u0939\u0948", "\u2581\u0914\u0930", "\u2581[", "SW", "IT", "CH", "_", "HI", "_", "EN", "]", "\u2581people", "\u2581[", "SW", "IT", "CH", "_", "EN", "_", "HI", "]", "\u2581\u092d", "\u094d", "\u2581\u0930", "\u092e\u094d", "\u2581[", "SW", "IT", "CH", "_", "HI", "_", "EN", "]", "\u2581se", "\u2581mut", "\u2581hok", "ar", "\u2581pride", "\u2581mah", "so", "os", "\u2581[", "SW", "IT", "CH", "_", "EN", "_", "HI", "]", "\u2581\u0915\u0930\u0924\u0947", "\u2581[", "SW", "IT", "CH", "_", "HI", "_", "EN", "]", "\u2581hain", "</s>"]}, {"text": "apki refuse ko [SWITCH_EN_HI] \u0926\u0947 \u0916\u094d \u0928\u0947 \u0915\u0947 [SWITCH_HI_EN] lie unhen permission mat den", "actual_class": 0, "actual_label": "negative", "predicted_class": 1, "predicted_label": "neutral", "confidence": null, "token_count": 35, "switch_token_count": 0, "attention_to_switch_tokens": null, "attention_from_switch_tokens": null, "token_texts": ["eng_Latn", "\u2581ap", "ki", "\u2581refuse", "\u2581ko", "\u2581[", "SW", "IT", "CH", "_", "EN", "_", "HI", "]", "\u2581\u0926\u0947", "\u2581\u0916", "\u094d", "\u2581\u0928\u0947", "\u2581\u0915\u0947", "\u2581[", "SW", "IT", "CH", "_", "HI", "_", "EN", "]", "\u2581lie", "\u2581un", "hen", "\u2581permission", "\u2581mat", "\u2581den", "</s>"]}, {"text": "any upakarnon par tab page menu [SWITCH_EN_HI] \u0915\u0947 [SWITCH_HI_EN] lie tab page [SWITCH_EN_HI] \u092a\u094d \u0930\u093f \u0936\u094d \u0925\u094d \u0905\u0915\u094d \u0936\u092e\u094d [SWITCH_HI_EN] karen", "actual_class": 1, "actual_label": "neutral", "predicted_class": 1, "predicted_label": "neutral", "confidence": null, "token_count": 60, "switch_token_count": 0, "attention_to_switch_tokens": null, "attention_from_switch_tokens": null, "token_texts": ["eng_Latn", "\u2581any", "\u2581up", "akar", "non", "\u2581par", "\u2581tab", "\u2581page", "\u2581menu", "\u2581[", "SW", "IT", "CH", "_", "EN", "_", "HI", "]", "\u2581\u0915\u0947", "\u2581[", "SW", "IT", "CH", "_", "HI", "_", "EN", "]", "\u2581lie", "\u2581tab", "\u2581page", "\u2581[", "SW", "IT", "CH", "_", "EN", "_", "HI", "]", "\u2581\u092a\u094d", "\u2581\u0930\u093f", "\u2581\u0936", "\u094d", "\u2581\u0925", "\u094d", "\u2581\u0905\u0915\u094d", "\u2581\u0936", "\u092e\u094d", "\u2581[", "SW", "IT", "CH", "_", "HI", "_", "EN", "]", "\u2581karen", "</s>"]}, {"text": "ends \u0915\u0947 \u0909\u0926\u094d \u0926\u0947 \u0936\u094d \u092f\u094b \u0928\u094d \u0915\u0940 [SWITCH_HI_EN] disposal se koson pendency, [SWITCH_EN_HI] \u0909\u0928\u0915\u093e anirnay [SWITCH_HI_EN] ya [SWITCH_EN_HI] \u092e\u0947 \u0930\u093f \u0924\u094d \u0938\u094d \u0915\u0947 \u0905\u0927\u0930\u094d [SWITCH_HI_EN] par niptan [SWITCH_EN_HI] \u0938\u0941 \u0928\u093f \u0936\u094d \u091a\u093f \u0924\u094d roop [SWITCH_HI_EN] se ends [SWITCH_EN_HI] \u0915\u0947 \u0909\u0926\u094d \u0926\u0947 \u0936\u094d \u092f\u094b \u0928\u094d [SWITCH_HI_EN] ko [SWITCH_EN_HI] \u0935\u093f \u092b\u0932\u094d \u0915\u0930 dega", "actual_class": 2, "actual_label": "positive", "predicted_class": 2, "predicted_label": "positive", "confidence": null, "token_count": 149, "switch_token_count": 0, "attention_to_switch_tokens": null, "attention_from_switch_tokens": null, "token_texts": ["eng_Latn", "\u2581ends", "\u2581\u0915\u0947", "\u2581\u0909\u0926\u094d", "\u2581\u0926\u0947", "\u2581\u0936", "\u094d", "\u2581\u092f\u094b", "\u2581\u0928\u094d", "\u2581\u0915\u0940", "\u2581[", "SW", "IT", "CH", "_", "HI", "_", "EN", "]", "\u2581dispos", "al", "\u2581se", "\u2581kos", "on", "\u2581p", "enden", "cy", ",", "\u2581[", "SW", "IT", "CH", "_", "EN", "_", "HI", "]", "\u2581\u0909\u0928\u0915\u093e", "\u2581an", "ir", "nay", "\u2581[", "SW", "IT", "CH", "_", "HI", "_", "EN", "]", "\u2581ya", "\u2581[", "SW", "IT", "CH", "_", "EN", "_", "HI", "]", "\u2581\u092e\u0947", "\u2581\u0930\u093f", "\u2581\u0924\u094d", "\u2581\u0938\u094d", "\u2581\u0915\u0947", "\u2581\u0905\u0927", "\u0930\u094d", "\u2581[", "SW", "IT", "CH", "_", "HI", "_", "EN", "]", "\u2581par", "\u2581ni", "pt", "an", "\u2581[", "SW", "IT", "CH", "_", "EN", "_", "HI", "]", "\u2581\u0938\u0941", "\u2581\u0928\u093f", "\u2581\u0936", "\u094d", "\u2581\u091a\u093f", "\u2581\u0924\u094d", "\u2581ro", "op", "\u2581[", "SW", "IT", "CH", "_", "HI", "_", "EN", "]", "\u2581se", "\u2581ends", "\u2581[", "SW", "IT", "CH", "_", "EN", "_", "HI", "]", "\u2581\u0915\u0947", "\u2581\u0909\u0926\u094d", "\u2581\u0926\u0947", "\u2581\u0936", "\u094d", "\u2581\u092f\u094b", "\u2581\u0928\u094d", "\u2581[", "SW", "IT", "CH", "_", "HI", "_", "EN", "]", "\u2581ko", "\u2581[", "SW", "IT", "CH", "_", "EN", "_", "HI", "]", "\u2581\u0935\u093f", "\u2581\u092b", "\u0932\u094d", "\u2581\u0915\u0930", "\u2581dega", "</s>"]}, {"text": "use apne creatures par poorn [SWITCH_EN_HI] \u0905\u0927\u093f \u0915\u0930\u094d prapt \u0939\u0948. \u0914\u0930 vah [SWITCH_HI_EN] wise, aware [SWITCH_EN_HI] \u0930\u0916\u094d \u0928\u0947 \u0935\u0932 \u0939\u0948", "actual_class": 2, "actual_label": "positive", "predicted_class": 1, "predicted_label": "neutral", "confidence": null, "token_count": 54, "switch_token_count": 0, "attention_to_switch_tokens": null, "attention_from_switch_tokens": null, "token_texts": ["eng_Latn", "\u2581use", "\u2581ap", "ne", "\u2581cre", "atures", "\u2581par", "\u2581po", "orn", "\u2581[", "SW", "IT", "CH", "_", "EN", "_", "HI", "]", "\u2581\u0905\u0927\u093f", "\u2581\u0915\u0930\u094d", "\u2581pra", "pt", "\u2581\u0939\u0948", ".", "\u2581\u0914\u0930", "\u2581vah", "\u2581[", "SW", "IT", "CH", "_", "HI", "_", "EN", "]", "\u2581wise", ",", "\u2581aware", "\u2581[", "SW", "IT", "CH", "_", "EN", "_", "HI", "]", "\u2581\u0930\u0916", "\u094d", "\u2581\u0928\u0947", "\u2581\u0935", "\u0932", "\u2581\u0939\u0948", "</s>"]}, {"text": "\u092f\u0926\u093f [SWITCH_HI_EN] yah [SWITCH_EN_HI] \u0914\u0930 pahle [SWITCH_HI_EN] ka [SWITCH_EN_HI] \u0928\u0939\u0940\u0902, [SWITCH_HI_EN] to [SWITCH_EN_HI] \u092d\u0940 [SWITCH_HI_EN] seventh century ka bana [SWITCH_EN_HI] \u0939\u0948 \u0914\u0930 earlier [SWITCH_HI_EN] mool roop se buddhist creed [SWITCH_EN_HI] \u0915\u0947 [SWITCH_HI_EN] lie tha, kintu bad men vishnu temple men [SWITCH_EN_HI] \u0930\u0941 \u092a\u0928\u094d \u0924\u094d \u0930\u093f \u0924\u094d \u0915\u0930 \u0926\u093f \u092f \u0917\u092f\u093e jismen [SWITCH_HI_EN] principal deity recumbent hue vishnu ya anantasayin hain", "actual_class": 1, "actual_label": "neutral", "predicted_class": 2, "predicted_label": "positive", "confidence": null, "token_count": 187, "switch_token_count": 0, "attention_to_switch_tokens": null, "attention_from_switch_tokens": null, "token_texts": ["eng_Latn", "\u2581\u092f\u0926\u093f", "\u2581[", "SW", "IT", "CH", "_", "HI", "_", "EN", "]", "\u2581yah", "\u2581[", "SW", "IT", "CH", "_", "EN", "_", "HI", "]", "\u2581\u0914\u0930", "\u2581pa", "hle", "\u2581[", "SW", "IT", "CH", "_", "HI", "_", "EN", "]", "\u2581ka", "\u2581[", "SW", "IT", "CH", "_", "EN", "_", "HI", "]", "\u2581\u0928\u0939\u0940\u0902", ",", "\u2581[", "SW", "IT", "CH", "_", "HI", "_", "EN", "]", "\u2581to", "\u2581[", "SW", "IT", "CH", "_", "EN", "_", "HI", "]", "\u2581\u092d\u0940", "\u2581[", "SW", "IT", "CH", "_", "HI", "_", "EN", "]", "\u2581se", "vent", "h", "\u2581century", "\u2581ka", "\u2581bana", "\u2581[", "SW", "IT", "CH", "_", "EN", "_", "HI", "]", "\u2581\u0939\u0948", "\u2581\u0914\u0930", "\u2581earlier", "\u2581[", "SW", "IT", "CH", "_", "HI", "_", "EN", "]", "\u2581mo", "ol", "\u2581ro", "op", "\u2581se", "\u2581bud", "dh", "ist", "\u2581cre", "ed", "\u2581[", "SW", "IT", "CH", "_", "EN", "_", "HI", "]", "\u2581\u0915\u0947", "\u2581[", "SW", "IT", "CH", "_", "HI", "_", "EN", "]", "\u2581lie", "\u2581tha", ",", "\u2581kintu", "\u2581bad", "\u2581men", "\u2581v", "ish", "nu", "\u2581temple", "\u2581men", "\u2581[", "SW", "IT", "CH", "_", "EN", "_", "HI", "]", "\u2581\u0930\u0941", "\u2581\u092a", "\u0928\u094d", "\u2581\u0924\u094d", "\u2581\u0930\u093f", "\u2581\u0924\u094d", "\u2581\u0915\u0930", "\u2581\u0926\u093f", "\u2581\u092f", "\u2581\u0917\u092f\u093e", "\u2581jis", "men", "\u2581[", "SW", "IT", "CH", "_", "HI", "_", "EN", "]", "\u2581principal", "\u2581de", "ity", "\u2581rec", "umb", "ent", "\u2581hue", "\u2581v", "ish", "nu", "\u2581ya", "\u2581an", "antas", "ayin", "\u2581hain", "</s>"]}, {"text": "\u0939\u092e\u0928\u0947 tumhen \u092a\u0948 \u0926 \u0915\u093f \u092f\u093e \u092b\u093f \u0930 [SWITCH_HI_EN] tum [SWITCH_EN_HI] \u0938\u091a \u0915\u094d \u092f\u094b \u0928\u094d \u0928\u0939\u0940\u0902 mante", "actual_class": 2, "actual_label": "positive", "predicted_class": 1, "predicted_label": "neutral", "confidence": null, "token_count": 36, "switch_token_count": 0, "attention_to_switch_tokens": null, "attention_from_switch_tokens": null, "token_texts": ["eng_Latn", "\u2581\u0939\u092e\u0928\u0947", "\u2581tum", "hen", "\u2581\u092a\u0948", "\u2581\u0926", "\u2581\u0915\u093f", "\u2581\u092f\u093e", "\u2581\u092b\u093f", "\u2581\u0930", "\u2581[", "SW", "IT", "CH", "_", "HI", "_", "EN", "]", "\u2581tum", "\u2581[", "SW", "IT", "CH", "_", "EN", "_", "HI", "]", "\u2581\u0938\u091a", "\u2581\u0915\u094d", "\u2581\u092f\u094b", "\u2581\u0928\u094d", "\u2581\u0928\u0939\u0940\u0902", "\u2581mante", "</s>"]}, {"text": "ap prat 10 baje vahan ho tej", "actual_class": 1, "actual_label": "neutral", "predicted_class": 1, "predicted_label": "neutral", "confidence": null, "token_count": 10, "switch_token_count": 0, "attention_to_switch_tokens": null, "attention_from_switch_tokens": null, "token_texts": ["eng_Latn", "\u2581ap", "\u2581prat", "\u258110", "\u2581baje", "\u2581va", "han", "\u2581ho", "\u2581tej", "</s>"]}, {"text": "\u0915\u0941 \u091b\u094d mahine [SWITCH_HI_EN] hue vahan normal democratic elections hue [SWITCH_EN_HI] \u0914\u0930 \u092b\u0932\u0938\u094d \u0935\u094d \u0930\u0941 \u092a\u094d vahan ek [SWITCH_HI_EN] popular radical party [SWITCH_EN_HI] \u0932\u094b \u0915\u092a\u094d \u0930\u093f \u092f\u094d \u092e\u094b \u0930\u094d \u091a- satta [SWITCH_HI_EN] men ayi", "actual_class": 2, "actual_label": "positive", "predicted_class": 0, "predicted_label": "negative", "confidence": null, "token_count": 88, "switch_token_count": 0, "attention_to_switch_tokens": null, "attention_from_switch_tokens": null, "token_texts": ["eng_Latn", "\u2581\u0915\u0941", "\u2581\u091b", "\u094d", "\u2581mah", "ine", "\u2581[", "SW", "IT", "CH", "_", "HI", "_", "EN", "]", "\u2581hue", "\u2581va", "han", "\u2581normal", "\u2581democrati", "c", "\u2581ele", "ctions", "\u2581hue", "\u2581[", "SW", "IT", "CH", "_", "EN", "_", "HI", "]", "\u2581\u0914\u0930", "\u2581\u092b\u0932", "\u0938\u094d", "\u2581\u0935\u094d", "\u2581\u0930\u0941", "\u2581\u092a\u094d", "\u2581va", "han", "\u2581ek", "\u2581[", "SW", "IT", "CH", "_", "HI", "_", "EN", "]", "\u2581popular", "\u2581radical", "\u2581party", "\u2581[", "SW", "IT", "CH", "_", "EN", "_", "HI", "]", "\u2581\u0932\u094b", "\u2581\u0915", "\u092a\u094d", "\u2581\u0930\u093f", "\u2581\u092f", "\u094d", "\u2581\u092e\u094b", "\u2581\u0930", "\u094d", "\u2581\u091a", "-", "\u2581sat", "ta", "\u2581[", "SW", "IT", "CH", "_", "HI", "_", "EN", "]", "\u2581men", "\u2581ayi", "</s>"]}]}}, "sample_processed_texts": ["module, ek program hoti [SWITCH_EN_HI] \u0939\u0948, jismen [SWITCH_HI_EN] ya to source code ya machine language [SWITCH_EN_HI] \u0915\u0947 [SWITCH_HI_EN] form men instructions nihit [SWITCH_EN_HI] \u0939\u094b \u0924\u0947 [SWITCH_HI_EN] hain.", "\u0914\u0930 \u0939\u092e\u0928\u0947 \u0914\u092e\u0947 samood \u0915\u0947 pas \u0909\u0928\u0915\u0947 \u092d\u093e \u0908 saleh [SWITCH_HI_EN] ko [SWITCH_EN_HI] \u092a\u0948 \u092e\u094d \u092c\u0930\u094d banakar \u092d\u0947 \u091c [SWITCH_HI_EN] to [SWITCH_EN_HI] \u0909\u0928\u094d \u0939\u094b\u0902 \u0928\u0947 apni [SWITCH_HI_EN] aum se kaha ae [SWITCH_EN_HI] \u092e\u0947 \u0930\u0940 [SWITCH_HI_EN] aum uda hi [SWITCH_EN_HI] \u0915\u0940 \u092a\u0930\u0938\u094d \u0924\u093f \u0936\u094d [SWITCH_HI_EN] karo uske siva koee tumhara mabood [SWITCH_EN_HI] \u0928\u0939\u0940\u0902 usi [SWITCH_HI_EN] ne tumko zamin [SWITCH_EN_HI] \u0915\u0940 mitti [SWITCH_HI_EN] se [SWITCH_EN_HI] \u092a\u0948 \u0926 \u0915\u093f \u092f\u093e \u0914\u0930 tumko usmen \u092c\u0938\u092f [SWITCH_HI_EN] to usse [SWITCH_EN_HI] \u092e\u092b\u093f \u0930\u0924\u094d \u0915\u0940 dua mgon \u092b\u093f \u0930 uski bargah [SWITCH_HI_EN] men [SWITCH_EN_HI] \u0924\u094c \u092c [SWITCH_HI_EN] karo [SWITCH_EN_HI] \u092c\u0947 \u0936\u0915\u094d \u092e\u0947 \u0930\u093e paravardigar har \u0936\u0936\u094d \u0915\u0947 [SWITCH_HI_EN] rib [SWITCH_EN_HI] \u0914\u0930 sabki sunta \u0914\u0930 dua ubool \u0915\u0930\u0924\u093e \u0939\u0948", "\u0914\u0930 [SWITCH_HI_EN] jab unhen yad [SWITCH_EN_HI] \u0926\u093f \u0932\u092f jata \u0939\u0948, [SWITCH_HI_EN] to ve yad [SWITCH_EN_HI] \u0928\u0939\u0940\u0902 \u0915\u0930\u0924\u0947,", "tumhen \u0968\u0966\u0967\u0967 ka ted prize mil [SWITCH_EN_HI] \u0917\u092f\u093e \u0939\u0948", "\u0909\u0928\u094d \u0939\u094b\u0902 \u0928\u0947 [SWITCH_HI_EN] bad science karne [SWITCH_EN_HI] \u0915\u0947 [SWITCH_HI_EN] lie ye delhi university [SWITCH_EN_HI] \u0915\u0947 \u0915\u093f \u0930\u094b \u0930\u093f \u092e\u0932\u094d [SWITCH_HI_EN] college [SWITCH_EN_HI] \u091a\u0932\u0947 [SWITCH_HI_EN] ge jahan [SWITCH_EN_HI] \u0907\u0928\u094d \u0939\u094b\u0902 \u0928\u0947 vijnjan [SWITCH_HI_EN] graduate [SWITCH_EN_HI] \u0915\u0940 [SWITCH_HI_EN] degree prapt [SWITCH_EN_HI] \u0915\u0940."]}, "pipeline_config": {"enabled": {"balanced_tokenization": true, "language_identification_tagging": false, "language_aware_normalization": true, "transliteration": false, "switch_point_encoding": true, "code_switch_augmentation": false, "context_aware_subword_sampling": false, "phonetic_normalization": true, "script_unification": false}, "pipeline_order": ["phonetic_normalization", "language_aware_normalization", "script_unification", "transliteration", "balanced_tokenization", "language_identification_tagging", "switch_point_encoding", "context_aware_subword_sampling"], "module_configs": {}, "random_seed": 42}, "mlflow_run_id": "569fd9853e6d47e48646361caeded459", "mlflow_experiment_id": "1"}